pyblackbirdbn/__init__.py
pyblackbirdbn-0.6.dist-info/LICENSE
pyblackbirdbn-0.6.dist-info/METADATA
pyblackbirdbn-0.6.dist-info/WHEEL
pyblackbirdbn-0.6.dist-info/top_level.txt
pyblackbirdbn-0.6.dist-info/zip-safe
pyblackbirdbn-0.6.dist-info/RECORD
