Metadata-Version: 2.1
Name: pyblackbirdbn
Version: 0.6
Summary: Python API for talking to Monoprice Blackbird 4k 8x8 HDBaseT Matrix
Home-page: https://github.com/b3tts32/pyblackbirdbn
Author: Rodney Betts
Author-email: rodneybetts@gmail.com
License: MIT
Download-URL: https://github.com/b3tts32/pyblackbirdbn/archive/0.6.tar.gz
Platform: UNKNOWN
Classifier: Development Status :: 4 - Beta
Classifier: Programming Language :: Python :: 3.5
Requires-Dist: pyserial (>=3.4)
Requires-Dist: pyserial-asyncio (>=0.4)
